{
  "id": "https://www.lassemempel.github.io/terminologies/technikthesaurus/9b4dd026-7a78-4d5b-a107-9eb554fa0414",
  "type": "Concept",
  "prefLabel": {
    "de": "einseitig gerader Stich"
  },
  "notation": [
    "9b4dd026-7a78-4d5b-a107-9eb554fa0414"
  ],
  "narrower": [
    {
      "id": "https://www.lassemempel.github.io/terminologies/technikthesaurus/690f50f7-8165-4100-a700-6bdf4ccb32b9",
      "prefLabel": {
        "de": "Gobelinstich"
      }
    },
    {
      "id": "https://www.lassemempel.github.io/terminologies/technikthesaurus/2b48af2e-dd3e-4fe8-b8eb-85bcd5b43796",
      "prefLabel": {
        "de": "Würfelstich"
      }
    },
    {
      "id": "https://www.lassemempel.github.io/terminologies/technikthesaurus/5573e179-8e3c-4b62-a3ba-5e55ddeb9a50",
      "prefLabel": {
        "de": "Pariser Stich"
      }
    },
    {
      "id": "https://www.lassemempel.github.io/terminologies/technikthesaurus/d291d235-cc21-49c3-818b-c3993ab72b86",
      "prefLabel": {
        "de": "Ungarischer Stich"
      }
    }
  ],
  "broader": {
    "id": "https://www.lassemempel.github.io/terminologies/technikthesaurus/fc13874d-708a-4db1-9110-832d84f557d5",
    "prefLabel": {
      "de": "gerader Stich"
    }
  },
  "inScheme": [
    {
      "id": "https://www.lassemempel.github.io/terminologies/technikthesaurus"
    }
  ],
  "inSchemeAll": [
    {
      "id": "https://www.lassemempel.github.io/terminologies/technikthesaurus"
    }
  ],
  "@context": {
    "@version": 1.1,
    "id": "@id",
    "type": "@type",
    "@vocab": "http://www.w3.org/2004/02/skos/core#",
    "xsd": "http://www.w3.org/2001/XMLSchema#",
    "dct": "http://purl.org/dc/terms/",
    "dc": "http://purl.org/dc/elements/1.1/",
    "schema": "https://schema.org/",
    "vann": "http://purl.org/vocab/vann/",
    "ldp": "http://www.w3.org/ns/ldp#",
    "owl": "http://www.w3.org/2002/07/owl#",
    "title": {
      "@id": "dct:title",
      "@container": "@language"
    },
    "dc:title": {
      "@id": "dc:title",
      "@container": "@language"
    },
    "dc:description": {
      "@id": "dc:description",
      "@container": "@language"
    },
    "description": {
      "@id": "dct:description",
      "@container": "@language"
    },
    "issued": {
      "@id": "dct:issued",
      "@type": "xsd:date"
    },
    "created": {
      "@id": "dct:created",
      "@type": "xsd:date"
    },
    "modified": {
      "@id": "dct:modified",
      "@type": "xsd:date"
    },
    "creator": "dct:creator",
    "publisher": "dct:publisher",
    "preferredNamespacePrefix": "vann:preferredNamespacePrefix",
    "preferredNamespaceUri": "vann:preferredNamespaceUri",
    "isBasedOn": "schema:isBasedOn",
    "source": "dct:source",
    "prefLabel": {
      "@container": "@language"
    },
    "altLabel": {
      "@container": [
        "@language",
        "@set"
      ]
    },
    "hiddenLabel": {
      "@container": [
        "@language",
        "@set"
      ]
    },
    "definition": {
      "@container": "@language"
    },
    "note": {
      "@container": [
        "@language",
        "@set"
      ]
    },
    "changeNote": {
      "@container": [
        "@language",
        "@set"
      ]
    },
    "editorialNote": {
      "@container": [
        "@language",
        "@set"
      ]
    },
    "historyNote": {
      "@container": [
        "@language",
        "@set"
      ]
    },
    "scopeNote": {
      "@container": [
        "@language",
        "@set"
      ]
    },
    "notation": {
      "@container": "@set"
    },
    "example": {
      "@container": "@language"
    },
    "narrower": {
      "@container": "@set"
    },
    "related": {
      "@container": "@set"
    },
    "relatedMatch": {
      "@container": "@set"
    },
    "narrowerTransitive": {
      "@container": "@set"
    },
    "broaderTransitive": {
      "@container": "@set"
    },
    "broadMatch": {
      "@container": "@set"
    },
    "narrowMatch": {
      "@container": "@set"
    },
    "closeMatch": {
      "@container": "@set"
    },
    "exactMatch": {
      "@container": "@set"
    },
    "hasTopConcept": {
      "@container": "@set"
    },
    "inScheme": {
      "@container": "@set"
    },
    "topConceptOf": {
      "@container": "@set"
    },
    "deprecated": {
      "@id": "owl:deprecated",
      "@type": "xsd:boolean"
    },
    "isReplacedBy": {
      "@id": "dct:isReplacedBy",
      "@container": "@set"
    }
  }
}